pytia.py
pytia-0.1.0.dist-info/DESCRIPTION.rst
pytia-0.1.0.dist-info/METADATA
pytia-0.1.0.dist-info/RECORD
pytia-0.1.0.dist-info/WHEEL
pytia-0.1.0.dist-info/metadata.json
pytia-0.1.0.dist-info/top_level.txt
