Metadata-Version: 2.0
Name: pytia
Version: 0.1.0
Summary: TOBI interface A server and client
Home-page: https://github.com/andrewramsay/pytia
Author: Andrew Ramsay
Author-email: andrew.ramsay@glasgow.ac.uk
License: MIT
Keywords: tobi tia acquisition signals
Platform: UNKNOWN
Classifier: Development Status :: 4 - Beta
Classifier: Intended Audience :: Developers
Classifier: License :: OSI Approved :: MIT License
Classifier: Programming Language :: Python :: 2
Classifier: Programming Language :: Python :: 2.7
Classifier: Programming Language :: Python :: 3
Classifier: Programming Language :: Python :: 3.3
Classifier: Programming Language :: Python :: 3.4
Classifier: Programming Language :: Python :: 3.5
